client/__init__.py
client/api/__init__.py
client/api/notebook.py
gofer/__init__.py
gofer/notebook.py
gofer/ok.py
gofer/utils.py
gofer_grader-1.1.0.dist-info/DESCRIPTION.rst
gofer_grader-1.1.0.dist-info/METADATA
gofer_grader-1.1.0.dist-info/RECORD
gofer_grader-1.1.0.dist-info/WHEEL
gofer_grader-1.1.0.dist-info/metadata.json
gofer_grader-1.1.0.dist-info/top_level.txt
