Metadata-Version: 2.0
Name: gofer-grader
Version: 1.1.0
Summary: Lightweight autograder for python files and notebooks
Home-page: UNKNOWN
Author: Vincent Su
Author-email: vipasu@berkeley.edu
License: 3-clause BSD
Platform: UNKNOWN
Requires-Dist: jinja2
Requires-Dist: pygments
Requires-Dist: tornado
